xontrib/rtx.py
xontrib_rtx-0.0.1.dist-info/LICENSE
xontrib_rtx-0.0.1.dist-info/WHEEL
xontrib_rtx-0.0.1.dist-info/METADATA
xontrib_rtx-0.0.1.dist-info/RECORD
