Metadata-Version: 2.1
Name: xontrib-rtx
Version: 0.0.1
Summary: Initializes rtx (polyglot asdf-like runtime manager)
Home-page: https://github.com/eugenesvk/xontrib-rtx
License: MIT
Keywords: xontrib,xonsh
Author: Evgeny
Author-email: es.bugzilla@gmail.com
Requires-Python: >=3.8
Classifier: Intended Audience :: Developers
Classifier: License :: OSI Approved :: MIT License
Classifier: Natural Language :: English
Classifier: Operating System :: OS Independent
Classifier: Programming Language :: Python :: 3
Classifier: Programming Language :: Python :: 3.8
Classifier: Programming Language :: Python :: 3.9
Classifier: Programming Language :: Python :: 3.10
Classifier: Programming Language :: Python :: 3.11
Classifier: Programming Language :: Python :: 3
Classifier: Topic :: System :: Shells
Classifier: Topic :: System :: System Shells
Classifier: Topic :: Terminals
Requires-Dist: xonsh (>=0.13.4)
Project-URL: Code, https://github.com/eugenesvk/xontrib-rtx
Project-URL: Documentation, https://github.com/eugenesvk/xontrib-rtx/blob/master/README.md
Project-URL: Issue tracker, https://github.com/eugenesvk/xontrib-rtx/issues
Project-URL: Repository, https://github.com/eugenesvk/xontrib-rtx
